strawberry_autograph/__init__.py
strawberry_autograph/main.py
strawberry_autograph-0.1.0.dist-info/LICENSE
strawberry_autograph-0.1.0.dist-info/METADATA
strawberry_autograph-0.1.0.dist-info/WHEEL
strawberry_autograph-0.1.0.dist-info/RECORD
