Metadata-Version: 2.1
Name: strawberry-autograph
Version: 0.1.0
Summary: A strawberry graphql schema wrapper with operation autogeneration.
Home-page: https://github.com/ryzhakar/strawberry-autograph
License: MIT
Keywords: strawberry-graphql,graphql,testing,autogeneration
Author: Arthur Ryzhak
Author-email: ryzhakar@gmail.com
Requires-Python: >=3.10,<4.0
Classifier: Development Status :: 3 - Alpha
Classifier: Intended Audience :: Developers
Classifier: License :: OSI Approved :: MIT License
Classifier: Operating System :: OS Independent
Classifier: Programming Language :: Python :: 3
Classifier: Programming Language :: Python :: 3.10
Classifier: Programming Language :: Python :: 3.11
Classifier: Programming Language :: Python :: 3.12
Classifier: Topic :: Software Development :: Libraries :: Python Modules
Classifier: Topic :: Software Development :: Testing
Requires-Dist: strawberry-graphql (>=0.209,<0.210)
Project-URL: Repository, https://github.com/ryzhakar/strawberry-autograph
